energy_cert/__init__.py
energy_cert/core.py
energy_cert/utils.py
energy_cert-0.1.1.dist-info/METADATA
energy_cert-0.1.1.dist-info/WHEEL
energy_cert-0.1.1.dist-info/top_level.txt
energy_cert-0.1.1.dist-info/RECORD
